features/__init__.py
features/steps/__init__.py
features/steps/dlt_pipelines.py
test/__init__.py
test/test_manage_jobs.py
workflow_sync/__init__.py
workflow_sync/ingest.py
workflow_sync/manage_jobs.py
workflow_sync/utils.py
workflow_sync/extract/__init__.py
workflow_sync/extract/export.py
workflow_sync/extract/gen_report.py
workflow_sync/pipelines/__init__.py
workflow_sync/pipelines/average_price/__init__.py
workflow_sync/pipelines/average_price/landing/__init__.py
workflow_sync/pipelines/average_price/landing/ingest_00.py
workflow_sync/pipelines/price_paid/__init__.py
workflow_sync/pipelines/price_paid/bronze_01.py
workflow_sync/pipelines/price_paid/gold_03.py
workflow_sync/pipelines/price_paid/ingest_00.py
workflow_sync/pipelines/price_paid/silver_02.py
workflow_sync-0.0.1.dist-info/LICENSE
workflow_sync-0.0.1.dist-info/METADATA
workflow_sync-0.0.1.dist-info/WHEEL
workflow_sync-0.0.1.dist-info/top_level.txt
workflow_sync-0.0.1.dist-info/RECORD
