Metadata-Version: 2.1
Name: workflow_sync
Version: 0.0.1
Summary: Sync databricks workflows
Home-page: http://zwio.com
Author: Daniel Humphreys
Author-email: Dan Humphreys <dan.humphreys@zwio.com>
License: The 3-Clause BSD License
Project-URL: Homepage, https://github.com/zwio-com/workflow-sync
Project-URL: Bug Tracker, https://github.com/zwio-com/workflow-sync/issues
Classifier: Programming Language :: Python :: 3
Classifier: License :: OSI Approved :: MIT License
Classifier: Operating System :: OS Independent
Requires-Python: >=3.10
License-File: LICENSE
